Metadata-Version: 2.1
Name: tulis
Version: 0.0.2
Summary: NULIS AUTOMATE
Home-page: https://github.com/krypton-byte/tulis-module
Author: Krypton Byte
Author-email: galaxyvplus6434@gmail.com
License: MIT
Download-URL: https://github.com/krypton-byte/tlis-module/archive/0.0.1.tar.gz
Keywords: nulis,tulis,writter,automate
Platform: UNKNOWN
Classifier: Development Status :: 3 - Alpha
Classifier: Intended Audience :: Developers
Classifier: Topic :: Software Development :: Build Tools
Classifier: License :: OSI Approved :: MIT License
Classifier: Programming Language :: Python :: 3.8
Classifier: Programming Language :: Python :: 3.9
